<annotation>
    <folder>label_txt</folder>
    <filename>114-broke-mosaic.jpg</filename>
    <path>/home/stoair/deep-learning-for-image-processing/pytorch_object_detection/faster_rcnn/VOCdevkit/VOC2012/label_txt/114-broke-mosaic.jpg</path>
    <source>
        <database>None</database>
    </source>
    <size>
        <width>1080</width>
        <height>1080</height>
        <depth>3</depth>
    </size>
    <segmented>0</segmented>
    <object>
        <name>broke</name>
        <pose>Unspecified</pose>
        <truncated>0</truncated>
        <difficult>0</difficult>
        <bndbox>
            <xmin>241</xmin>
            <ymin>88</ymin>
            <xmax>492</xmax>
            <ymax>329</ymax>
        </bndbox>
    </object>
    <object>
        <name>broke</name>
        <pose>Unspecified</pose>
        <truncated>0</truncated>
        <difficult>0</difficult>
        <bndbox>
            <xmin>17</xmin>
            <ymin>489</ymin>
            <xmax>355</xmax>
            <ymax>746</ymax>
        </bndbox>
    </object>
    <object>
        <name>broke</name>
        <pose>Unspecified</pose>
        <truncated>0</truncated>
        <difficult>0</difficult>
        <bndbox>
            <xmin>635</xmin>
            <ymin>697</ymin>
            <xmax>918</xmax>
            <ymax>776</ymax>
        </bndbox>
    </object>
    <object>
        <name>broke</name>
        <pose>Unspecified</pose>
        <truncated>0</truncated>
        <difficult>0</difficult>
        <bndbox>
            <xmin>765</xmin>
            <ymin>226</ymin>
            <xmax>924</xmax>
            <ymax>289</ymax>
        </bndbox>
    </object>
</annotation>
