<annotation>
    <folder>label_txt</folder>
    <filename>473-good-mosaic.jpg</filename>
    <path>/home/stoair/deep-learning-for-image-processing/pytorch_object_detection/faster_rcnn/VOCdevkit/VOC2012/label_txt/473-good-mosaic.jpg</path>
    <source>
        <database>None</database>
    </source>
    <size>
        <width>1080</width>
        <height>1080</height>
        <depth>3</depth>
    </size>
    <segmented>0</segmented>
    <object>
        <name>good</name>
        <pose>Unspecified</pose>
        <truncated>0</truncated>
        <difficult>0</difficult>
        <bndbox>
            <xmin>402</xmin>
            <ymin>437</ymin>
            <xmax>544</xmax>
            <ymax>534</ymax>
        </bndbox>
    </object>
    <object>
        <name>good</name>
        <pose>Unspecified</pose>
        <truncated>0</truncated>
        <difficult>0</difficult>
        <bndbox>
            <xmin>374</xmin>
            <ymin>835</ymin>
            <xmax>628</xmax>
            <ymax>991</ymax>
        </bndbox>
    </object>
    <object>
        <name>good</name>
        <pose>Unspecified</pose>
        <truncated>0</truncated>
        <difficult>0</difficult>
        <bndbox>
            <xmin>639</xmin>
            <ymin>845</ymin>
            <xmax>876</xmax>
            <ymax>972</ymax>
        </bndbox>
    </object>
    <object>
        <name>good</name>
        <pose>Unspecified</pose>
        <truncated>0</truncated>
        <difficult>0</difficult>
        <bndbox>
            <xmin>649</xmin>
            <ymin>83</ymin>
            <xmax>1080</xmax>
            <ymax>342</ymax>
        </bndbox>
    </object>
</annotation>
