<annotation>
    <folder>label_txt</folder>
    <filename>well0_0259.jpg</filename>
    <path>/home/stoair/deep-learning-for-image-processing/pytorch_object_detection/faster_rcnn/VOCdevkit/VOC2012/label_txt/well0_0259.jpg</path>
    <source>
        <database>None</database>
    </source>
    <size>
        <width>600</width>
        <height>800</height>
        <depth>3</depth>
    </size>
    <segmented>0</segmented>
    <object>
        <name>good</name>
        <pose>Unspecified</pose>
        <truncated>0</truncated>
        <difficult>0</difficult>
        <bndbox>
            <xmin>25</xmin>
            <ymin>117</ymin>
            <xmax>566</xmax>
            <ymax>628</ymax>
        </bndbox>
    </object>
</annotation>
