<annotation>
    <folder>VOC</folder>
    <filename>149-uc-mosaic</filename>
    <source>
        <database>My Database</database>
        <annotation>COCO</annotation>
        <image>flickr</image>
        <flickrid>NULL</flickrid>
    </source>
    <owner>
        <flickrid>NULL</flickrid>
        <name>company</name>
    </owner>
    <size>
        <width>1080</width>
        <height>1080</height>
        <depth>3</depth>
    </size>
    <segmented>0</segmented>
    <object>
        <name>uncovered</name>
        <pose>Unspecified</pose>
        <truncated>0</truncated>
        <difficult>0</difficult>
        <bndbox>
            <xmin>278</xmin>
            <ymin>31</ymin>
            <xmax>511</xmax>
            <ymax>277</ymax>
        </bndbox>
    </object>
    <object>
        <name>uncovered</name>
        <pose>Unspecified</pose>
        <truncated>0</truncated>
        <difficult>0</difficult>
        <bndbox>
            <xmin>124</xmin>
            <ymin>892</ymin>
            <xmax>484</xmax>
            <ymax>990</ymax>
        </bndbox>
    </object>
    <object>
        <name>good</name>
        <pose>Unspecified</pose>
        <truncated>0</truncated>
        <difficult>0</difficult>
        <bndbox>
            <xmin>18</xmin>
            <ymin>1032</ymin>
            <xmax>287</xmax>
            <ymax>1080</ymax>
        </bndbox>
    </object>
    <object>
        <name>uncovered</name>
        <pose>Unspecified</pose>
        <truncated>0</truncated>
        <difficult>0</difficult>
        <bndbox>
            <xmin>789</xmin>
            <ymin>732</ymin>
            <xmax>1080</xmax>
            <ymax>1005</ymax>
        </bndbox>
    </object>
</annotation>