<annotation>
    <folder>VOC</folder>
    <filename>VOCdevkit\VOC2007/JPEGImages\152.jpg</filename>
    <source>
        <database>My Database</database>
        <annotation>COCO</annotation>
        <image>flickr</image>
        <flickrid>NULL</flickrid>
    </source>
    <owner>
        <flickrid>NULL</flickrid>
        <name>company</name>
    </owner>
    <size>
        <width>1080</width>
        <height>1080</height>
        <depth>3</depth>
    </size>
    <segmented>0</segmented>
    <object>
        <name>lose</name>
        <pose>Unspecified</pose>
        <truncated>0</truncated>
        <difficult>0</difficult>
        <bndbox>
            <xmin>341</xmin>
            <ymin>0</ymin>
            <xmax>609</xmax>
            <ymax>164</ymax>
        </bndbox>
    </object>
    <object>
        <name>lose</name>
        <pose>Unspecified</pose>
        <truncated>0</truncated>
        <difficult>0</difficult>
        <bndbox>
            <xmin>230</xmin>
            <ymin>986</ymin>
            <xmax>614</xmax>
            <ymax>1080</ymax>
        </bndbox>
    </object>
    <object>
        <name>lose</name>
        <pose>Unspecified</pose>
        <truncated>0</truncated>
        <difficult>0</difficult>
        <bndbox>
            <xmin>800</xmin>
            <ymin>552</ymin>
            <xmax>976</xmax>
            <ymax>748</ymax>
        </bndbox>
    </object>
    <object>
        <name>lose</name>
        <pose>Unspecified</pose>
        <truncated>0</truncated>
        <difficult>0</difficult>
        <bndbox>
            <xmin>671</xmin>
            <ymin>0</ymin>
            <xmax>885</xmax>
            <ymax>241</ymax>
        </bndbox>
    </object>
</annotation>
