<annotation>
    <folder>VOC</folder>
    <filename>VOCdevkit\VOC2007/JPEGImages\311.jpg</filename>
    <source>
        <database>My Database</database>
        <annotation>COCO</annotation>
        <image>flickr</image>
        <flickrid>NULL</flickrid>
    </source>
    <owner>
        <flickrid>NULL</flickrid>
        <name>company</name>
    </owner>
    <size>
        <width>1080</width>
        <height>1080</height>
        <depth>3</depth>
    </size>
    <segmented>0</segmented>
    <object>
        <name>good</name>
        <pose>Unspecified</pose>
        <truncated>0</truncated>
        <difficult>0</difficult>
        <bndbox>
            <xmin>169</xmin>
            <ymin>258</ymin>
            <xmax>349</xmax>
            <ymax>459</ymax>
        </bndbox>
    </object>
    <object>
        <name>good</name>
        <pose>Unspecified</pose>
        <truncated>0</truncated>
        <difficult>0</difficult>
        <bndbox>
            <xmin>38</xmin>
            <ymin>908</ymin>
            <xmax>274</xmax>
            <ymax>1055</ymax>
        </bndbox>
    </object>
    <object>
        <name>good</name>
        <pose>Unspecified</pose>
        <truncated>0</truncated>
        <difficult>0</difficult>
        <bndbox>
            <xmin>495</xmin>
            <ymin>979</ymin>
            <xmax>670</xmax>
            <ymax>1080</ymax>
        </bndbox>
    </object>
    <object>
        <name>good</name>
        <pose>Unspecified</pose>
        <truncated>0</truncated>
        <difficult>0</difficult>
        <bndbox>
            <xmin>373</xmin>
            <ymin>63</ymin>
            <xmax>1021</xmax>
            <ymax>420</ymax>
        </bndbox>
    </object>
</annotation>
