<annotation>
    <folder>VOC</folder>
    <filename>VOCdevkit\VOC2007/JPEGImages\337.jpg</filename>
    <source>
        <database>My Database</database>
        <annotation>COCO</annotation>
        <image>flickr</image>
        <flickrid>NULL</flickrid>
    </source>
    <owner>
        <flickrid>NULL</flickrid>
        <name>company</name>
    </owner>
    <size>
        <width>1080</width>
        <height>1080</height>
        <depth>3</depth>
    </size>
    <segmented>0</segmented>
    <object>
        <name>circle</name>
        <pose>Unspecified</pose>
        <truncated>0</truncated>
        <difficult>0</difficult>
        <bndbox>
            <xmin>0</xmin>
            <ymin>0</ymin>
            <xmax>349</xmax>
            <ymax>65</ymax>
        </bndbox>
    </object>
    <object>
        <name>circle</name>
        <pose>Unspecified</pose>
        <truncated>0</truncated>
        <difficult>0</difficult>
        <bndbox>
            <xmin>0</xmin>
            <ymin>521</ymin>
            <xmax>219</xmax>
            <ymax>693</ymax>
        </bndbox>
    </object>
    <object>
        <name>circle</name>
        <pose>Unspecified</pose>
        <truncated>0</truncated>
        <difficult>0</difficult>
        <bndbox>
            <xmin>417</xmin>
            <ymin>653</ymin>
            <xmax>609</xmax>
            <ymax>763</ymax>
        </bndbox>
    </object>
    <object>
        <name>circle</name>
        <pose>Unspecified</pose>
        <truncated>0</truncated>
        <difficult>0</difficult>
        <bndbox>
            <xmin>500</xmin>
            <ymin>34</ymin>
            <xmax>847</xmax>
            <ymax>304</ymax>
        </bndbox>
    </object>
</annotation>
