<annotation>
    <folder>VOC</folder>
    <filename>111-uc</filename>
    <source>
        <database>My Database</database>
        <annotation>COCO</annotation>
        <image>flickr</image>
        <flickrid>NULL</flickrid>
    </source>
    <owner>
        <flickrid>NULL</flickrid>
        <name>company</name>
    </owner>
    <size>
        <width>640</width>
        <height>640</height>
        <depth>3</depth>
    </size>
    <segmented>0</segmented>
    <object>
        <name>uncovered</name>
        <pose>Unspecified</pose>
        <truncated>0</truncated>
        <difficult>0</difficult>
        <bndbox>
            <xmin>91</xmin>
            <ymin>312</ymin>
            <xmax>339</xmax>
            <ymax>415</ymax>
        </bndbox>
    </object>
</annotation>