<annotation>
    <folder>VOC</folder>
    <filename>358-good-mosaic</filename>
    <source>
        <database>My Database</database>
        <annotation>COCO</annotation>
        <image>flickr</image>
        <flickrid>NULL</flickrid>
    </source>
    <owner>
        <flickrid>NULL</flickrid>
        <name>company</name>
    </owner>
    <size>
        <width>1080</width>
        <height>1080</height>
        <depth>3</depth>
    </size>
    <segmented>0</segmented>
    <object>
        <name>good</name>
        <pose>Unspecified</pose>
        <truncated>0</truncated>
        <difficult>0</difficult>
        <bndbox>
            <xmin>0</xmin>
            <ymin>153</ymin>
            <xmax>415</xmax>
            <ymax>633</ymax>
        </bndbox>
    </object>
    <object>
        <name>good</name>
        <pose>Unspecified</pose>
        <truncated>0</truncated>
        <difficult>0</difficult>
        <bndbox>
            <xmin>84</xmin>
            <ymin>989</ymin>
            <xmax>488</xmax>
            <ymax>1080</ymax>
        </bndbox>
    </object>
    <object>
        <name>good</name>
        <pose>Unspecified</pose>
        <truncated>0</truncated>
        <difficult>0</difficult>
        <bndbox>
            <xmin>752</xmin>
            <ymin>982</ymin>
            <xmax>937</xmax>
            <ymax>1080</ymax>
        </bndbox>
    </object>
    <object>
        <name>good</name>
        <pose>Unspecified</pose>
        <truncated>0</truncated>
        <difficult>0</difficult>
        <bndbox>
            <xmin>642</xmin>
            <ymin>92</ymin>
            <xmax>948</xmax>
            <ymax>423</ymax>
        </bndbox>
    </object>
</annotation>